MANIFEST.in
README.txt
setup.py
bin/wscrap
pyscrap/__init__.py
pyscrap/item.py
pyscrap/pipeline.py
pyscrap/settings.py
pyscrap/spiders.py
pyscrap/templates.py
pyscrap.egg-info/PKG-INFO
pyscrap.egg-info/SOURCES.txt
pyscrap.egg-info/dependency_links.txt
pyscrap.egg-info/requires.txt
pyscrap.egg-info/top_level.txt