Metadata-Version: 1.1
Name: pyscrap
Version: 0.0.6
Summary: micro framework for web scraping
Home-page: http://github.com/Nievous/pyscrap
Author: Daniel Mondaca
Author-email: daniel@analitic.cl
License: Apache 2.0 License
Keywords: web scraping
Platform: UNKNOWN
Classifier: Development Status :: 4 - Beta
Classifier: Topic :: Software Development
Classifier: License :: OSI Approved :: Apache Software License
Classifier: Operating System :: POSIX :: Linux
Classifier: Programming Language :: Python
